dbt/adapters/analyticdb/__init__.py
dbt/adapters/analyticdb/__version__.py
dbt/adapters/analyticdb/column.py
dbt/adapters/analyticdb/connections.py
dbt/adapters/analyticdb/impl.py
dbt/adapters/analyticdb/relation.py
dbt/adapters/mariadb/__init__.py
dbt/adapters/mariadb/__version__.py
dbt/adapters/mariadb/column.py
dbt/adapters/mariadb/connections.py
dbt/adapters/mariadb/impl.py
dbt/adapters/mariadb/relation.py
dbt/adapters/mysql5/__init__.py
dbt/adapters/mysql5/__version__.py
dbt/adapters/mysql5/column.py
dbt/adapters/mysql5/connections.py
dbt/adapters/mysql5/impl.py
dbt/adapters/mysql5/relation.py
dbt/include/analyticdb/__init__.py
dbt/include/analyticdb/dbt_project.yml
dbt/include/analyticdb/sample_profiles.yml
dbt/include/analyticdb/macros/adapters.sql
dbt/include/analyticdb/macros/catalog.sql
dbt/include/analyticdb/macros/materializations/incremental/helpers.sql
dbt/include/analyticdb/macros/materializations/incremental/incremental.sql
dbt/include/analyticdb/macros/materializations/seed/seed.sql
dbt/include/analyticdb/macros/materializations/snapshot/snapshot.sql
dbt/include/analyticdb/macros/materializations/snapshot/snapshot_merge.sql
dbt/include/analyticdb/macros/materializations/snapshot/strategies.sql
dbt/include/analyticdb/macros/materializations/test/test.sql
dbt/include/mariadb/__init__.py
dbt/include/mariadb/dbt_project.yml
dbt/include/mariadb/sample_profiles.yml
dbt/include/mariadb/macros/adapters.sql
dbt/include/mariadb/macros/catalog.sql
dbt/include/mariadb/macros/materializations/incremental/helpers.sql
dbt/include/mariadb/macros/materializations/incremental/incremental.sql
dbt/include/mariadb/macros/materializations/seed/seed.sql
dbt/include/mariadb/macros/materializations/snapshot/snapshot.sql
dbt/include/mariadb/macros/materializations/snapshot/snapshot_merge.sql
dbt/include/mariadb/macros/materializations/snapshot/strategies.sql
dbt/include/mariadb/macros/materializations/test/test.sql
dbt/include/mysql5/__init__.py
dbt_analyticdb-0.0.9.dist-info/LICENSE
dbt_analyticdb-0.0.9.dist-info/METADATA
dbt_analyticdb-0.0.9.dist-info/WHEEL
dbt_analyticdb-0.0.9.dist-info/top_level.txt
dbt_analyticdb-0.0.9.dist-info/RECORD
